{"img":[{"tit":"그림 1","content":"더할나위없는 그림 1번 입니다.","src":"../img/p1.jpg"},{"tit":"그림 2","content":"더할나위없는 그림 2번 입니다.","src":"../img/p2.jpg"},{"tit":"그림 3","content":"더할나위없는 그림 3번 입니다.","src":"../img/p3.jpg"},{"tit":"그림 4","content":"더할나위없는 그림 4번 입니다.","src":"../img/p4.jpg"},{"tit":"그림 5","content":"더할나위없는 그림 5번 입니다.","src":"../img/p5.jpg"},{"tit":"그림 6","content":"더할나위없는 그림 6번 입니다.","src":"../img/p6.jpg"},{"tit":"그림 7","content":"더할나위없는 그림 7번 입니다.","src":"../img/p7.jpg"},{"tit":"그림 8","content":"더할나위없는 그림 8번 입니다.","src":"../img/p8.jpg"}],"cnt":8}